laboro_ssh/__init__.py
laboro_ssh/schema/__init__.py
laboro_ssh/schema/specification.yml
laboro_ssh-0.0.8.dist-info/LICENSE
laboro_ssh-0.0.8.dist-info/METADATA
laboro_ssh-0.0.8.dist-info/WHEEL
laboro_ssh-0.0.8.dist-info/top_level.txt
laboro_ssh-0.0.8.dist-info/RECORD
